dls_pmacanalyse/__init__.py
dls_pmacanalyse/__main__.py
dls_pmacanalyse/_version.py
dls_pmacanalyse/analyse.py
dls_pmacanalyse/dls_pmacanalyse.py
dls_pmacanalyse/errors.py
dls_pmacanalyse/factorySettings_geobrick.pmc
dls_pmacanalyse/factorySettings_pmac.pmc
dls_pmacanalyse/globalconfig.py
dls_pmacanalyse/pmac.py
dls_pmacanalyse/pmaclexer.py
dls_pmacanalyse/pmacparser.py
dls_pmacanalyse/pmacprogram.py
dls_pmacanalyse/pmacstate.py
dls_pmacanalyse/pmacvariables.py
dls_pmacanalyse/utils.py
dls_pmacanalyse/webpage.py
dls_pmacanalyse-3.0.0.dist-info/LICENSE
dls_pmacanalyse-3.0.0.dist-info/METADATA
dls_pmacanalyse-3.0.0.dist-info/WHEEL
dls_pmacanalyse-3.0.0.dist-info/entry_points.txt
dls_pmacanalyse-3.0.0.dist-info/top_level.txt
dls_pmacanalyse-3.0.0.dist-info/RECORD
